README.md
setup.cfg
setup.py
gevent_serial.egg-info/PKG-INFO
gevent_serial.egg-info/SOURCES.txt
gevent_serial.egg-info/dependency_links.txt
gevent_serial.egg-info/entry_points.txt
gevent_serial.egg-info/requires.txt
gevent_serial.egg-info/top_level.txt
gserial/__init__.py
gserial/base.py
gserial/exception.py
gserial/loop.py
gserial/posix.py
gserial/rs485.py
gserial/ser2tcp.py
gserial/util.py
gserial/rfc2217/__init__.py
gserial/rfc2217/client.py
gserial/rfc2217/manager.py