Metadata-Version: 2.1
Name: gevent-serial
Version: 0.2.3
Summary: A gevent friendly serial line
Home-page: https://github.com/tiagocoutinho/gserial
Author: Tiago Coutinho
Author-email: coutinhotiago@gmail.com
License: GPL
Keywords: pyserial,gevent
Platform: UNKNOWN
Classifier: Development Status :: 2 - Pre-Alpha
Classifier: Intended Audience :: Developers
Classifier: Natural Language :: English
Classifier: Programming Language :: Python :: 2
Classifier: Programming Language :: Python :: 2.7
Classifier: Programming Language :: Python :: 3
Classifier: Programming Language :: Python :: 3.5
Classifier: Programming Language :: Python :: 3.6
Classifier: Programming Language :: Python :: 3.7
Provides-Extra: ser2tcp
